geo/__init__.py
geo/admindiv.py
geo/cities.py
geo/countries.py
locales/__init__.py
locales/currencies.py
locales/languages.py
locales/timezone.py
utils/__init__.py
utils/config.py
utils/helpers.py
geodbpyclient-1.1.1.dist-info/LICENSE.md
geodbpyclient-1.1.1.dist-info/METADATA
geodbpyclient-1.1.1.dist-info/WHEEL
geodbpyclient-1.1.1.dist-info/top_level.txt
geodbpyclient-1.1.1.dist-info/RECORD
