Metadata-Version: 2.1
Name: geodbpyclient
Version: 1.1.1
Summary: Python package for a university course
Home-page: https://git.e-science.pl/kwazny_252716_dpp/kwazny252716_dpp_python_pip
Author: Karol Ważny
Author-email: kwazny_252716@e-science.pl
License: MIT
Platform: UNKNOWN
License-File: LICENSE.md
Requires-Dist: requests
